goldstar/__init__.py
GoldStar-1.0.1.dist-info/METADATA
GoldStar-1.0.1.dist-info/WHEEL
GoldStar-1.0.1.dist-info/top_level.txt
GoldStar-1.0.1.dist-info/RECORD
