Metadata-Version: 2.1
Name: GoldStar
Version: 1.0.1
Summary: API for website.goldstar.cf
Author: GoldStar
Classifier: Programming Language :: Python :: 3
Classifier: License :: OSI Approved :: MIT License
Classifier: Operating System :: OS Independent
Requires-Python: >=3.6
Requires-Dist: aiohttp
